comparador_secuencial_b.v
module comparador_secuencial_b (
    input wire [7:0] A,      // Primer número a comparar
    input wire [7:0] B,      // Segundo número a comparar
    input wire clk,          // Reloj
    output reg q,            // Salida: 1 cuando A > B
    output reg q_lt          // Salida: 1 cuando A < B
);

    always @(posedge clk) begin
        if (A > B) begin
            q <= 1'b1;
            q_lt <= 1'b0;
        end else if (A < B) begin
            q <= 1'b0;
            q_lt <= 1'b1;
        end else begin
            q <= 1'b0;
            q_lt <= 1'b0;
        end
    end

endmodule

comparador_secuencial_b_tb.v
`timescale 1ns/1ps

module comparador_secuencial_b_tb;

    // Entradas del DUT (Device Under Test)
    reg [7:0] A;
    reg [7:0] B;
    reg clk;

    // Salidas del DUT
    wire q;
    wire q_lt;

    // Instancia del módulo comparador_secuencial
    comparador_secuencial_b UUT (
        .A(A),
        .B(B),
        .clk(clk),
        .q(q),
        .q_lt(q_lt)
    );

    // Generación de la señal de reloj (50 MHz)
    always #10 clk = ~clk;

    // Procedimiento de testeo
    initial begin
        // Inicializar señales
        clk = 0;
        A = 8'b00000000;
        B = 8'b00000000;

        // Prueba 1: A > B
        #20;
        A = 8'b00010010;  // A = 18
        B = 8'b00001010;  // B = 10
        #20;

        // Prueba 2: A < B
        A = 8'b00001010;  // A = 10
        B = 8'b00010010;  // B = 18
        #20;

        // Prueba 3: A == B
        A = 8'b00100100;  // A = 36
        B = 8'b00100100;  // B = 36
        #20;

        // Finalizar la simulación
        $finish;
    end

    // Guardar resultados en un archivo para visualización en GTKWave
    initial begin
        $dumpfile("comparador_secuencial_b_tb.vcd");
        $dumpvars;
    
    end

endmodule

comparador_secuencial_b_tb.vcd
$date
	Fri Aug 30 22:16:18 2024
$end
$version
	Icarus Verilog
$end
$timescale
	1ps
$end
$scope module comparador_secuencial_b_tb $end
$var wire 1 ! q_lt $end
$var wire 1 " q $end
$var reg 8 # A [7:0] $end
$var reg 8 $ B [7:0] $end
$var reg 1 % clk $end
$scope module UUT $end
$var wire 8 & A [7:0] $end
$var wire 8 ' B [7:0] $end
$var wire 1 % clk $end
$var reg 1 " q $end
$var reg 1 ! q_lt $end
$upscope $end
$upscope $end
$enddefinitions $end
#0
$dumpvars
b0 '
b0 &
0%
b0 $
b0 #
x"
x!
$end
#10000
0!
0"
1%
#20000
0%
b1010 $
b1010 '
b10010 #
b10010 &
#30000
1"
1%
#40000
0%
b10010 $
b10010 '
b1010 #
b1010 &
#50000
1!
0"
1%
#60000
0%
b100100 $
b100100 '
b100100 #
b100100 &
#70000
0!
1%
