ejercicio4.v
module ejercicio4(
    input x, clk, reset,
    output reg z
);

parameter A = 3'b000,
          B = 3'b001,
          C = 3'b010,
          D = 3'b011,
          E = 3'b100;

reg [2:0] current_state=A, next_state=A;

always @(posedge clk, posedge reset)
begin
    if(reset)
        current_state <= A;
    else
        current_state <= next_state;
end

always @(current_state, x)
begin
    z = 0;
    case(current_state)
        A: 
            if (x == 1)
                next_state = A;
            else
                next_state = B;
        B: 
            if (x == 1)
                next_state = C;
            else
                next_state = B;
        C: 
            if (x == 1)
                next_state = B;
            else
                next_state = D;
        D: 
            if (x == 1)
                next_state = C;
            else
                next_state = E;
        E: 
            if (x == 1)
            begin
                z = 1;
                next_state = A;
            end
            else
                next_state = B;
    endcase
end
endmodule

ejercicio4_tb.v
`timescale 1ns / 1ps
module ejercicio4_tb;
  reg x=0;
  reg clk=0;
  wire z;

    always begin
        #1 clk = !clk;
    end

    ejercicio4 ej40 (.clk(clk), .x(x), .z(z));

    initial begin
        $dumpfile("ejercicio4_tb.vcd");
        $dumpvars;
#2 
x=0;
#2 
x=1;
#2 
x=0;
#2 
x=0;
#2 
x=1;
#100
x=1;
#2 
x=1;
#2 
x=1;
#2 
x=1;
#100
x = 0;

    
    // Fin de la simulación
    #1000 $finish;
    end
endmodule

ejercicio4_tb.vcd
$date
	Sat Sep 28 15:35:54 2024
$end
$version
	Icarus Verilog
$end
$timescale
	1ps
$end
$scope module ejercicio4_tb $end
$var wire 1 ! z $end
$var reg 1 " clk $end
$var reg 1 # x $end
$scope module ej40 $end
$var wire 1 " clk $end
$var wire 1 $ reset $end
$var wire 1 # x $end
$var reg 3 % current_state [2:0] $end
$var reg 3 & next_state [2:0] $end
$var reg 1 ! z $end
$upscope $end
$upscope $end
$enddefinitions $end
#0
$dumpvars
b1 &
b0 %
z$
0#
0"
0!
$end
#1000
b1 %
1"
#2000
0"
#3000
1"
#4000
b10 &
0"
1#
#5000
b1 &
b10 %
1"
#6000
b11 &
0"
0#
#7000
b100 &
b11 %
1"
#8000
0"
#9000
b1 &
b100 %
1"
#10000
b0 &
1!
0"
1#
#11000
0!
b0 %
1"
